epub_browser/__init__.py
epub_browser/library.py
epub_browser/main.py
epub_browser/processor.py
epub_browser/server.py
epub_browser/watch.py
epub_browser/assets/book.css
epub_browser/assets/book.js
epub_browser/assets/chapter.css
epub_browser/assets/chapter.js
epub_browser/assets/fa-solid-900.woff2
epub_browser/assets/fa.all.min.css
epub_browser/assets/favion.svg
epub_browser/assets/github-dark.min.css
epub_browser/assets/github.min.css
epub_browser/assets/highlight.min.js
epub_browser/assets/library.css
epub_browser/assets/library.js
epub_browser/assets/sortable.min.js
epub_browser-1.6.14.dist-info/METADATA
epub_browser-1.6.14.dist-info/WHEEL
epub_browser-1.6.14.dist-info/entry_points.txt
epub_browser-1.6.14.dist-info/top_level.txt
epub_browser-1.6.14.dist-info/RECORD
