Metadata-Version: 2.4
Name: epub-browser
Version: 1.6.14
Summary: A tool to open epub files and serve them via a local web server for reading in a browser on any device.
Home-page: https://github.com/dfface/epub-browser
Author: dfface
Author-email: dfface@sina.com
Keywords: epub reader html export browser convert calibre-web calibre kindle web server local
Classifier: Programming Language :: Python :: 3
Classifier: License :: OSI Approved :: MIT License
Classifier: Operating System :: OS Independent
Requires-Python: >=3.6
Requires-Dist: tqdm
Requires-Dist: minify-html
Requires-Dist: watchdog
Dynamic: author
Dynamic: author-email
Dynamic: classifier
Dynamic: description
Dynamic: description-content-type
Dynamic: home-page
Dynamic: keywords
Dynamic: requires-dist
Dynamic: requires-python
Dynamic: summary
